[{"title": "The Soviets were planning this from the beginning.", "text": "", "date": "2017-01-31", "comments": [{"text": "#Upvote this comment if this is a **DANK MEME**. Downvote this comment if this is a **NORMIE MEME**.", "date": "2017-01-31"}, {"text": "Seize... the means of production?", "date": "2017-02-01"}, {"text": "Friccin dank", "date": "2017-02-01"}]}, {"title": "ALLES HIER IST MEIN", "text": "", "date": "2017-01-30", "comments": [{"text": "#Upvote this comment if this is a **DANK MEME**. Downvote this comment if this is a **NORMIE MEME**.", "date": "2017-01-30"}, {"text": "#\u0345\u0318\u034e\u034e\u033c\u035a\u033b\u0334\u035d\u0328\u0328\u0341 \u0325\u0320\u032a\u034eA\u036c\u0344\u030b\u0312\u0366\u0367\u0300\u0319\u0361\u0489\u0315\u034fL\u034a\u030f\u030d\u0309\u0310\u0339\u0323\u0317\u0347\u0322L\u0332\u0353\u034e\u035e\u035d\u035d\u0340 \u030f\u0366\u0309\u0342\u0317\u0349\u032b\u034d\u0319\u0360\u0334\u0335\u0335\u0489Y\u033d\u0363\u0365\u034a\u0302\u031d\u031e\u0355\u032d\u0329\u031d\u0336\u0341O\u031b\u0335\u0338\u034f\u0321U\u0300\u030c\u0349\u0326\u031e\u0338\u035f\u0315\u035d\u0315R\u0346\u0363\u0312\u0369\u0346\u0303\u0306\u0353\u031f\u0332\u0326\u0328\u0327 \u030e\u0339\u0316\u0321F\u032f\u0325\u031b\u0328\u0335\u0334\u035c\u0341\u035cE\u0357\u034f\u0322\u0322\u0321\u0340\u034f\u034fE\u0365\u0342\u034b\u030f\u0309\u032c\u0337\u035cL\u031c\u0489\u0358I\u0313\u0301\u0305\u033a\u034e\u0323\u0347\u0328N\u0368\u031a\u031a\u033e\u0310\u0355\u0353\u033a\u0323\u031c\u0317\u0341\u0340\u0335\u0335\u0322\u035eG\u034c\u0342\u036c\u0313\u030d\u0368\u0332\u032f\u032c\u031f\u034d\u032d\u0336\u0340\u0362S\u034c\u0303\u0312\u030e\u0330\u032e\u034e\u031c\u034f\u0327 \u0313\u030f\u0308\u0301\u0363\u036c\u031e\u034d\u0333\u032d\u032b\u0319\u0320\u0328\u0335\u0334\u035f\u0361\u035e\u0336A\u034b\u036a\u0345\u0324\u031f\u034e\u0319\u032f\u0316\u0335\u0362R\u035b\u033a\u0326\u0329\u034e\u0337\u0328\u034fE\u030a\u0310\u030f\u0307\u0359\u032a\u0356\u0339\u0320\u032b\u0326\u035e\u0315\u0338\u0315\u0361 \u0365\u0343\u0319\u0354\u0330\u0354\u0334\u035eM\u0367\u030b\u0363\u032c\u0316I\u0311\u0324\u0355\u0489\u035eN\u0342\u031a\u034c\u035a\u0359\u031e\u0316\u0345\u035d\u0334\u0334\u0361E\u036c\u0311\u0326\u0326\u0320\u032d\u0317\u031d\u0326\u0328\u0489 \u030e\u0312\u0314\u0301\u030b\u034b\u0331\u032a\u031f\u0318\u035d\u0337\u0336", "date": "2017-01-31"}, {"text": "Meins*", "date": "2017-01-31"}]}, {"title": "Damn, the spy's baguette hits scout's mom pretty hard", "text": "", "date": "2017-01-29", "comments": [{"text": "#Upvote this comment if this is a **DANK MEME**. Downvote this comment if this is a **NORMIE MEME**.", "date": "2017-01-29"}, {"text": "Stolen meme", "date": "2017-02-03"}]}, {"title": "Italian Title", "text": "", "date": "2017-01-28", "comments": [{"text": "#Upvote this comment if this is a **DANK MEME**. Downvote this comment if this is a **NORMIE MEME**.", "date": "2017-01-29"}, {"text": "N\nO\nR\nM\nI\nE", "date": "2017-01-29"}]}, {"title": "When the mods get a little too ballsy", "text": "", "date": "2017-01-27", "comments": [{"text": "#Upvote this comment if this is a **DANK MEME**. Downvote this comment if this is a **NORMIE MEME**.", "date": "2017-01-28"}, {"text": "[removed]", "date": "2017-01-28"}]}, {"title": "NORMIE", "text": "", "date": "2017-01-26", "comments": []}, {"title": "Not My President", "text": "", "date": "2017-01-25", "comments": [{"text": "Fuckin dank", "date": "2017-01-26"}, {"text": "Damn he beat her so hard she turned black", "date": "2017-01-26"}, {"text": "That's so dank I can taste it", "date": "2017-01-26"}, {"text": "am Donald trump and I approve this meme", "date": "2017-01-26"}, {"text": "I approve this meme", "date": "2017-01-26"}, {"text": "I mean this is pretty accurate. I don't like him but that doesn't mean I'm delusional enough to not accept reality. ", "date": "2017-01-26"}, {"text": "Dank as fuck", "date": "2017-01-26"}, {"text": "Shit, I've seen this on 4 chan. Should have posted it...", "date": "2017-01-26"}, {"text": "Dank", "date": "2017-01-26"}, {"text": "Not my dank ", "date": "2017-01-26"}, {"text": "Approve approve approve", "date": "2017-01-26"}, {"text": "Great memeee boii [8.4/10]", "date": "2017-01-26"}, {"text": "Trump isn't my President tho.\n\nLiterally\n\nI'm Canadian", "date": "2017-01-26"}, {"text": "Confirmed\n", "date": "2017-01-26"}, {"text": "White women protesting =/= black dude being beaten stale memes booo", "date": "2017-01-26"}, {"text": "Please dont let this sub turn into /r/cringeanarchy", "date": "2017-01-26"}, {"text": "I mean he was demoted...", "date": "2017-01-26"}, {"text": "This sub is becoming way too much like /r/Imgoingtohellforthis", "date": "2017-01-26"}, {"text": "Dankie", "date": "2017-01-26"}, {"text": "Donk aflac", "date": "2017-01-26"}, {"text": "Trump isn't your president? What the fuck are you still here for?", "date": "2017-01-26"}, {"text": "normie", "date": "2017-01-26"}, {"text": "Is he playing growtopia on his PC?", "date": "2017-01-26"}, {"text": "[Similar?](http://imgur.com/svE3VWR) \n\n[Indeed.](http://imgur.com/nEugwdC) ", "date": "2017-01-26"}, {"text": "\"Now go on the forums and cry like the little bitch you are!\"", "date": "2017-01-26"}]}, {"title": "A good taste in music", "text": "", "date": "2017-01-24", "comments": []}, {"title": "Guys!!! Check out this antique photo of Orville Wright I just found in my grandma's basement", "text": "", "date": "2017-01-23", "comments": []}, {"title": "Oh shit JK Rowling just joined the great meme war", "text": "", "date": "2017-01-22", "comments": []}, {"title": "When you show up at the party but your friends pretend not to see you", "text": "", "date": "2017-01-21", "comments": [{"text": "EIN MEME F\u00dcR NORMIES", "date": "2017-01-22"}]}, {"title": "JihadiNeistat back at it again", "text": "", "date": "2017-01-20", "comments": [{"text": "I can't remember the last time I laughed so hard at a meme.", "date": "2017-01-21"}, {"text": "can we please meme about casey neistat ", "date": "2017-01-21"}, {"text": "Probably the best meme i have ever seen", "date": "2017-01-21"}, {"text": "Dank", "date": "2017-01-21"}, {"text": ">666,420\n\nIncredible", "date": "2017-01-21"}, {"text": "Photoshopped- that isn't even the white house ", "date": "2017-01-21"}, {"text": "Boiiii he bout to do it ", "date": "2017-01-21"}, {"text": "He's a jew though. Not a Muslim. He would just plan and fund the whole thing \ud83d\ude02", "date": "2017-01-21"}, {"text": "BOI", "date": "2017-01-21"}, {"text": "Yabba dabba doo", "date": "2017-01-21"}, {"text": "His PC gaming channel's name would be CaseyNiceStats", "date": "2017-01-21"}]}, {"title": "hey guys its michelle", "text": "", "date": "2017-01-19", "comments": [{"text": "#Upvote this comment if this is a **DANK MEME**. Downvote this comment if this is a **NORMIE MEME**.", "date": "2017-01-20"}]}, {"title": "*title", "text": "", "date": "2017-01-18", "comments": [{"text": "#Upvote this comment if this is a **DANK MEME**. Downvote this comment if this is a **NORMIE MEME**.", "date": "2017-01-18"}]}, {"title": "when cancer gets you", "text": "", "date": "2017-01-17", "comments": [{"text": "#Upvote this comment if this is a **DANK MEME**. Downvote this comment if this is a **NORMIE MEME**.", "date": "2017-01-18"}]}, {"title": "Communist", "text": "", "date": "2017-01-16", "comments": [{"text": "#Upvote this comment if this is a **DANK MEME**. Downvote this comment if this is a **NORMIE MEME**.", "date": "2017-01-16"}]}, {"title": "For lack of a better name", "text": "", "date": "2017-01-15", "comments": [{"text": "#Upvote this comment if this is a **DANK MEME**. Downvote this comment if this is a **NORMIE MEME**.", "date": "2017-01-15"}, {"text": "This isn't technically a repost. It's me improving my own meme. *still drinks bleach*", "date": "2017-01-15"}, {"text": "Dank", "date": "2017-01-16"}]}, {"title": "Jack be nimble, Jack be quick", "text": "", "date": "2017-01-14", "comments": [{"text": "Upvote this comment if this is a dank meme. Downvote this comment if this is a normie meme.", "date": "2017-01-15"}, {"text": "HE BOOT TOO BIG FOR HE GOTDAMN FEET", "date": "2017-01-15"}]}, {"title": "\ud83d\udc4f\ud83d\udc4f\ud83d\udc4f\ud83d\udc4f\ud83d\udc4f\ud83d\udc4f", "text": "", "date": "2017-01-13", "comments": [{"text": "# Upvote this comment if this is a dank meme. Downvote this comment if this is a normie meme. Your votes count!", "date": "2017-01-14"}]}, {"title": "too dank \ud83d\udcaf\ud83d\udcaf\ud83d\udcaf\ud83d\udcaf\ud83d\udcaf\ud83d\udcaf\ud83d\udcaf", "text": "", "date": "2017-01-12", "comments": [{"text": "# Upvote this comment if this is a dank meme. Downvote this comment if this is a normie meme. Your votes count!", "date": "2017-01-13"}, {"text": "Dank", "date": "2017-01-13"}]}, {"title": "RIP", "text": "", "date": "2017-01-11", "comments": [{"text": "Dank", "date": "2017-01-12"}, {"text": "Somebody ring the dankster", "date": "2017-01-12"}, {"text": "# Upvote this comment if this is a dank meme. Downvote this comment if this is a normie meme. Your votes count!", "date": "2017-01-12"}]}, {"title": "Mista wurldwajd", "text": "", "date": "2017-01-10", "comments": [{"text": "Dank", "date": "2017-01-11"}]}, {"title": "q", "text": "", "date": "2017-01-09", "comments": [{"text": "# Upvote this comment if this is a dank meme. Downvote this comment if this is a normie meme. Your votes count!", "date": "2017-01-10"}, {"text": "holy shit that's an old picture, beta 1.2", "date": "2017-01-10"}, {"text": "now thats what i call art", "date": "2017-01-10"}, {"text": "Marx would be proud.", "date": "2017-01-10"}, {"text": "Dank", "date": "2017-01-10"}, {"text": "Denk", "date": "2017-01-10"}, {"text": "Okay but why did he need the same block in two different slots?", "date": "2017-01-10"}, {"text": "/r/fullcommunism", "date": "2017-01-10"}, {"text": "Bamboozled", "date": "2017-01-10"}]}, {"title": "You like jazz?", "text": "", "date": "2017-01-08", "comments": [{"text": "# Upvote this comment if this is a dank meme. Downvote this comment if this is a normie meme. Your votes count!", "date": "2017-01-08"}, {"text": "Robbie's smile is so beautiful... ", "date": "2017-01-09"}, {"text": "I now know what I'm doing tonight. ", "date": "2017-01-09"}, {"text": "Dank", "date": "2017-01-09"}, {"text": "My favourite anime is finally available <#333", "date": "2017-01-09"}, {"text": "Holy fuck it is\n[woah](https://i.imgur.com/6LErP9T.png) ", "date": "2017-01-09"}, {"text": "Denk", "date": "2017-01-09"}]}, {"title": "emoji movie cancer", "text": "", "date": "2017-01-07", "comments": [{"text": "This scared me, I had to make sure it wasn't real.", "date": "2017-01-08"}, {"text": "Dank", "date": "2017-01-08"}, {"text": "gay", "date": "2017-01-08"}]}, {"title": "*record scratch* *freeze frame*", "text": "", "date": "2017-01-06", "comments": [{"text": "# Upvote this comment if this is a dank meme. Downvote this comment if this is a normie meme. Your votes count!", "date": "2017-01-07"}, {"text": "Dank", "date": "2017-01-07"}]}, {"title": "Times a changing", "text": "", "date": "2017-01-05", "comments": [{"text": "# Upvote this comment if this is a dank meme. Downvote this comment if this is a normie meme. Your votes count!", "date": "2017-01-06"}, {"text": "You've got to dank yourself one question: \"Do I feel dank?\" Well, do ya, punk?", "date": "2017-01-06"}, {"text": "Dank", "date": "2017-01-06"}]}, {"title": "Those Russians\u2026 at it again.", "text": "", "date": "2017-01-04", "comments": [{"text": "# Upvote this comment if this is a dank meme (shit's dank son). Downvote this comment if this is a normie meme (throw it in the trash). Your votes count!", "date": "2017-01-04"}, {"text": "Hillary looks high af", "date": "2017-01-05"}, {"text": "Kill me please...my dank existence is a nightmare", "date": "2017-01-04"}, {"text": "Dank", "date": "2017-01-05"}]}, {"title": "Holy shit! They changed it again!", "text": "", "date": "2017-01-03", "comments": [{"text": "# Upvote this comment if this is a dank meme (shit's dank son). Downvote this comment if this is a normie meme (throw it in the trash).", "date": "2017-01-04"}, {"text": "Dank Memes are a hell of a drug.", "date": "2017-01-04"}, {"text": "Dank", "date": "2017-01-04"}, {"text": "You cuck stole my idea rot in danke hell", "date": "2017-01-04"}]}, {"title": "Gain is lemonain", "text": "", "date": "2017-01-02", "comments": [{"text": "#UPVOTE this comment if this is a **DANK MEME** (shits dank son). DOWNVOTE this comment if this is **NORMIE MEME** (throw it in the trash).\nDank transdimensional reptilian shape shifting cyber AI bots from the Alpha Centauri star system will remove or approve all posts based on **your** votes on this comment!\n\n*I am a bot, and this action was performed automatically. Please [contact the moderators of this subreddit](/message/compose/?to=/r/dankmemes) if you have any questions or concerns.*", "date": "2017-01-02"}, {"text": "Dank", "date": "2017-01-03"}]}, {"title": "Not dank current events meme", "text": "", "date": "2017-01-01", "comments": [{"text": "Hey, if you feel like this is a normie meme, downvote this comment. If you feel that it's a dank meme, upvote this comment. We have a bot that will remove the submission if this reaches -3 upvotes after one hour, so your votes do count!\n\n*I am a bot, and this action was performed automatically. Please [contact the moderators of this subreddit](/message/compose/?to=/r/dankmemes) if you have any questions or concerns.*", "date": "2017-01-01"}, {"text": "To dank or not to dank, that is the question", "date": "2017-01-02"}, {"text": "Dank", "date": "2017-01-02"}]}]